dueros_smarthome/__init__.py
dueros_smarthome/client.py
dueros_smarthome/const.py
dueros_smarthome/models.py
dueros_smarthome-0.0.15.dist-info/METADATA
dueros_smarthome-0.0.15.dist-info/WHEEL
dueros_smarthome-0.0.15.dist-info/licenses/LICENSE
dueros_smarthome-0.0.15.dist-info/RECORD
