Metadata-Version: 2.1
Name: dueros_smarthome
Version: 0.0.15
Summary: Duer OS SmartHome APIs
Project-URL: Homepage, https://github.com/zsy056/dueros-smarthome
Project-URL: Bug Tracker, https://github.com/zsy056/dueros-smarthome/issues
Author-email: Shaoyu Zhang <zsy056@gmail.com>
License-File: LICENSE
Classifier: License :: OSI Approved :: MIT License
Classifier: Operating System :: OS Independent
Classifier: Programming Language :: Python :: 3
Requires-Python: >=3.7
Requires-Dist: httpx
